izisat/__init__.py
izisat/izisentinel.py
izisat/teste.py
izisat/misc/__init__.py
izisat/misc/connections.py
izisat/misc/dates.py
izisat/misc/dto.py
izisat/misc/files.py
izisat/misc/raster_processing.py
izisat/misc/utils.py
izisat-1.0.18.dist-info/licenses/LICENSE
izisat-1.0.18.dist-info/METADATA
izisat-1.0.18.dist-info/WHEEL
izisat-1.0.18.dist-info/top_level.txt
izisat-1.0.18.dist-info/RECORD
