Metadata-Version: 2.4
Name: izisat
Version: 1.0.18
Summary: Add your description here
Requires-Python: >=3.12
License-File: LICENSE
Requires-Dist: geopandas>=1.1.1
Requires-Dist: loguru>=0.7.3
Requires-Dist: rasterio>=1.4.3
Requires-Dist: requests>=2.32.4
Requires-Dist: s2cloudless>=1.7.3
Requires-Dist: tqdm>=4.67.1
Dynamic: license-file
